whitecloak/__init__.py
whitecloak/__main__.py
whitecloak/main.py
whitecloak-0.4.3.dist-info/METADATA
whitecloak-0.4.3.dist-info/WHEEL
whitecloak-0.4.3.dist-info/entry_points.txt
whitecloak-0.4.3.dist-info/RECORD
