Metadata-Version: 2.1
Name: whitecloak
Version: 0.4.3
Summary: 
Author: Jeremy Berman
Author-email: jerber@sas.upenn.edu
Requires-Python: >=3.10,<4.0
Classifier: Programming Language :: Python :: 3
Classifier: Programming Language :: Python :: 3.10
Classifier: Programming Language :: Python :: 3.11
Classifier: Programming Language :: Python :: 3.12
Requires-Dist: devtools (>=0.12.2,<0.13.0)
Requires-Dist: httpx (>=0.27.0,<0.28.0)
Requires-Dist: pydantic (>=2.7.0,<3.0.0)
Requires-Dist: typer[all] (>=0.12.3,<0.13.0)
